{
  "metadata": {
    "parsingConfidence": 66.7,
    "lastUpdated": "2025-07-31T15:09:41.922012",
    "validityPeriod": {
      "start": "2025-06-12T00:00:00",
      "end": "2025-09-04T00:00:00"
    },
    "validityDate": "12JUN2025",
    "source": "ERSA",
    "version": "1.0"
  },
  "data": {
    "icao": "YBRY",
    "name": "BARIMUNYA",
    "firefighting": {
      "category": null,
      "availability": null
    },
    "runways": [
      {
        "designation": "10/28",
        "length": 6400,
        "width": 30,
        "surface": "Asphalt",
        "lighting": [
          "LIRL",
          "PAPI",
          "PTBL"
        ],
        "ends": {}
      }
    ],
    "navaids": [],
    "lighting": [
      {
        "runway": "10/28",
        "type": "LIRL",
        "end": "both"
      },
      {
        "runway": "10/28",
        "type": "PAPI",
        "end": "both"
      },
      {
        "runway": "10/28",
        "type": "PTBL",
        "end": "both"
      }
    ]
  }
}