{
  "metadata": {
    "parsingConfidence": 66.7,
    "lastUpdated": "2025-09-08T10:19:39.268674",
    "validityPeriod": {
      "start": "2025-09-04T00:00:00",
      "end": "2025-11-27T00:00:00"
    },
    "validityDate": "04SEP2025",
    "source": "ERSA",
    "version": "1.0"
  },
  "data": {
    "icao": "YJLC",
    "name": "JULIA CREEK",
    "state": "QLD",
    "country": "AU",
    "latitude": -36.4267,
    "longitude": 148.6017,
    "elevation": 404,
    "firefighting": {
      "category": null,
      "availability": null
    },
    "runways": [
      {
        "designation": "10/28",
        "length": 4600,
        "width": 30,
        "surface": "Asphalt",
        "lighting": [
          "LIRL"
        ],
        "ends": {}
      }
    ],
    "navaids": [],
    "lighting": [
      {
        "runway": "10/28",
        "type": "LIRL",
        "end": "both"
      }
    ]
  }
}