{
  "metadata": {
    "parsingConfidence": 100.0,
    "lastUpdated": "2025-09-08T10:24:13.936771",
    "validityPeriod": {
      "start": "2025-09-04T00:00:00",
      "end": "2025-11-27T00:00:00"
    },
    "validityDate": "04SEP2025",
    "source": "ERSA",
    "version": "1.0"
  },
  "data": {
    "icao": "YPEA",
    "name": "PEARCE",
    "state": "WA",
    "country": "AU",
    "latitude": -31.6678,
    "longitude": 116.015,
    "elevation": 150,
    "firefighting": {
      "category": "CAT 5",
      "availability": null
    },
    "runways": [
      {
        "designation": "05/23",
        "length": 5500,
        "width": 45,
        "surface": "Asphalt",
        "lighting": [
          "MIRL",
          "PTBL"
        ],
        "ends": {}
      },
      {
        "designation": "18L/36R",
        "length": 9800,
        "width": 45,
        "surface": "Asphalt",
        "lighting": [
          "MIRL",
          "PTBL"
        ],
        "ends": {
          "18L": {
            "PAPI": true
          },
          "36R": {
            "PAPI": true
          }
        }
      },
      {
        "designation": "18R/36L",
        "length": 5700,
        "width": 30,
        "surface": "Asphalt",
        "lighting": [],
        "ends": {
          "36L": {}
        }
      }
    ],
    "navaids": [
      {
        "type": "ILS/DME",
        "ident": "IPC",
        "freq": 111.9,
        "runway": "36R"
      },
      {
        "type": "ILS/DME",
        "ident": "IPE",
        "freq": 110.7,
        "runway": "18L"
      },
      {
        "type": "NDB",
        "ident": "PEA",
        "freq": 340.0
      },
      {
        "type": "TAC",
        "ident": "PEA",
        "freq": 112.8
      }
    ],
    "lighting": [
      {
        "runway": "05/23",
        "type": "MIRL",
        "end": "both"
      },
      {
        "runway": "05/23",
        "type": "PTBL",
        "end": "both"
      },
      {
        "runway": "18L/36R",
        "type": "MIRL",
        "end": "both"
      },
      {
        "runway": "18L/36R",
        "type": "PTBL",
        "end": "both"
      },
      {
        "runway": "18L",
        "type": "PAPI",
        "end": "both"
      },
      {
        "runway": "36R",
        "type": "PAPI",
        "end": "both"
      }
    ]
  }
}